{
  "project": {
    "title": "s2-st4-elle-2"
  },
  "output": {
    "width": 1080,
    "height": 1920,
    "fps": 30,
    "video_bitrate": "4M"
  },
  "style": {
    "background_color": "#be185d",
    "text_color": "#ffffff"
  },
  "scenes": [
    {
      "duration_sec": 1.5,
      "text": "Ce n'est pas ce téléphone qui te fait peur. C'est TOUS les téléphones.",
      "gradient": [
        "#be185d",
        "#1c1917"
      ]
    },
    {
      "duration_sec": 1.5,
      "text": "C'est la fois où tu as découvert la première conversation. C'est la fois où un sourire devant un écran a changé ta vie.",
      "gradient": [
        "#1c1917",
        "#1c1917"
      ]
    },
    {
      "duration_sec": 2.0,
      "text": "Le téléphone n'est pas le problème.",
      "gradient": [
        "#1c1917",
        "#be185d"
      ],
      "subtitle": "Le passé est le problème."
    },
    {
      "duration_sec": 1.5,
      "text": "Ton corps a parlé ?",
      "subtitle": "3 questions gratuites → captainbond.com",
      "gradient": [
        "#be185d",
        "#1c1917"
      ]
    },
    {
      "duration_sec": 1.5,
      "text": "CAPTAIN BOND",
      "subtitle": "des questions qui connectent",
      "gradient": [
        "#be185d",
        "#1c1917"
      ]
    }
  ],
  "description": "Ce n'est pas ce téléphone qui te fait peur. C'est TOUS les téléphones. C'est la fois où tu as découvert la première conversation. C'est la fois où un sourire devant un écran a changé ta vie. Le téléphone n'est pas le problème. Le passé est le problème.\n\n→ Dis-le en commentaire\n→ Tag ton partenaire\n\n3 questions gratuites → captainbond.com\n\n#couple #origines #attachement"
}